{
  "title": "Getting Started",
  "description": "Learn how how to set-up Argo Workflows and run you first workflow.",
  "difficulty": "Beginner",
  "time": "15m",
  "details": {
    "steps": [
      {
        "title": "Installing Argo Workflows",
        "text": "install.md"
      },
      {
        "title": "What is a workflow?",
        "text": "workflow.md"
      },
      {
        "title": "Using the UI",
        "text": "ui.md"
      },
      {
        "title": "Using the CLI",
        "text": "cli.md"
      }
    ],
    "intro": {
      "text": "intro.md"
    },
    "finish": {
      "text": "finish.md"
    }
  },
  "environment": {
    "uilayout": "terminal-iframe",
    "showdashboard": true,
    "dashboards": [
      {
        "name": "Argo Server",
        "port": "2746"
      }
    ]
  },
  "backend": {
    "imageid": "kubernetes-cluster-running:1.18"
  }
}